newbar_afisha
