Metadata-Version: 1.0
Name: newbar-afisha
Version: 0.0.7
Summary: CLI util for quick-look for recent events in New Bar (ekb)
Home-page: https://github.com/strizhechenko/newbar-afisha
Author: Oleg Strizhechenko
Author-email: oleg.strizhechenko@gmail.com
License: GPL
Platform: UNKNOWN
